LICENSE.txt
README.md
tornado_sqlalchemy/__init__.py
tornado_sqlalchemy-0.8.0.dist-info/LICENSE.txt
tornado_sqlalchemy-0.8.0.dist-info/METADATA
tornado_sqlalchemy-0.8.0.dist-info/WHEEL
tornado_sqlalchemy-0.8.0.dist-info/RECORD
